agent.py
html_screenshot.py
vibecheck_agent-0.2.9.dist-info/METADATA
vibecheck_agent-0.2.9.dist-info/WHEEL
vibecheck_agent-0.2.9.dist-info/entry_points.txt
vibecheck_agent-0.2.9.dist-info/top_level.txt
vibecheck_agent-0.2.9.dist-info/RECORD
