Metadata-Version: 2.4
Name: vibecheck-agent
Version: 0.2.9
Summary: Slack에서 Claude Code를 원격 제어하는 Agent
Author-email: VibeCheck <hello@vibecheck.dev>
License: MIT
Project-URL: Homepage, https://vibecheck.nestoz.co
Project-URL: Repository, https://github.com/NestozAI/VibeCheck
Classifier: Development Status :: 4 - Beta
Classifier: Intended Audience :: Developers
Classifier: License :: OSI Approved :: MIT License
Classifier: Programming Language :: Python :: 3
Classifier: Programming Language :: Python :: 3.9
Classifier: Programming Language :: Python :: 3.10
Classifier: Programming Language :: Python :: 3.11
Classifier: Programming Language :: Python :: 3.12
Requires-Python: >=3.9
Requires-Dist: websockets>=12.0
Provides-Extra: screenshot
Requires-Dist: playwright>=1.40.0; extra == "screenshot"
